<?xmp version="1.0" encoding="UTF-8" standalone="yes"?>
<TaskModel xmlns="http://giove.isti.cnr.it/ctt" xmlns:coop="http://giove.isti.cnr.it/cttcoop" NameTaskModelID="Display personal information">
    <Task Identifier="Display personal information" Category="abstraction" Iterative="false" Optional="false" PartOfCooperation="false" Frequency=" ">
        <Name>name</Name>
        <SubTask>
            <Task Identifier="Access user profile" Category="interaction" Iterative="false" Optional="false" PartOfCooperation="false" Frequency=" ">
                <Name>name</Name>
                <TemporalOperator name="SequentialEnabling"/>
                <Parent name="Display personal information"/>
                <SiblingRight name="Display nickname"/>
            </Task>
            <Task Identifier="Display nickname" Category="application" Iterative="false" Optional="false" PartOfCooperation="false" Frequency=" ">
                <Name>name</Name>
                <TemporalOperator name="OrderIndependence"/>
                <Parent name="Display personal information"/>
                <SiblingLeft name="Access user profile"/>
                <SiblingRight name="Display age"/>
            </Task>
            <Task Identifier="Display age" Category="application" Iterative="false" Optional="false" PartOfCooperation="false" Frequency=" ">
                <Name>name</Name>
                <TemporalOperator name="OrderIndependence"/>
                <Parent name="Display personal information"/>
                <SiblingLeft name="Display nickname"/>
                <SiblingRight name="Display location"/>
            </Task>
            <Task Identifier="Display location" Category="application" Iterative="false" Optional="false" PartOfCooperation="false" Frequency=" ">
                <Name>name</Name>
                <TemporalOperator name="OrderIndependence"/>
                <Parent name="Display personal information"/>
                <SiblingLeft name="Display age"/>
                <SiblingRight name="Display gender"/>
            </Task>
            <Task Identifier="Display gender" Category="application" Iterative="false" Optional="false" PartOfCooperation="false" Frequency=" ">
                <Name>name</Name>
                <TemporalOperator name="OrderIndependence"/>
                <Parent name="Display personal information"/>
                <SiblingLeft name="Display location"/>
                <SiblingRight name="Display picture"/>
            </Task>
            <Task Identifier="Display picture" Category="application" Iterative="false" Optional="false" PartOfCooperation="false" Frequency=" ">
                <Name>name</Name>
                <Parent name="Display personal information"/>
                <SiblingLeft name="Display gender"/>
            </Task>
        </SubTask>
    </Task>
</TaskModel>
